addr/__init__.py
addr/shell/__init__.py
addr/shell/usage.py
addr/src/temp.txt
package_name/__init__.py
package_name/shell/__init__.py
package_name/shell/usage.py
package_name/src/temp.txt
addr-0.0.1.dist-info/LICENSE
addr-0.0.1.dist-info/METADATA
addr-0.0.1.dist-info/WHEEL
addr-0.0.1.dist-info/entry_points.txt
addr-0.0.1.dist-info/top_level.txt
addr-0.0.1.dist-info/zip-safe
addr-0.0.1.dist-info/RECORD
